testnabila/__init__.py
testnabila/antispoofing_model.h5
testnabila/antispoofing_model.json
testnabila/f_liveness_detection.py
testnabila/f_orientation_detection.py
testnabila/f_utils.py
testnabila/haarcascade_frontalface_default.xml
testnabila/liveness.py
testnabila/ocr.py
testnabila/haarcascades/haarcascade_frontalface_alt.xml
testnabila/haarcascades/haarcascade_profileface.xml
testnabila-0.0.27.dist-info/LICENSE
testnabila-0.0.27.dist-info/METADATA
testnabila-0.0.27.dist-info/WHEEL
testnabila-0.0.27.dist-info/top_level.txt
testnabila-0.0.27.dist-info/RECORD
