Metadata-Version: 2.1
Name: testnabila
Version: 0.0.27
Summary: This repository contains a Python program designed to execute Optical Character Recognition (OCR) and Facial Recognition on images.
Home-page: 
Author: Nabila Lasri
Author-email: lasri.nabilait@gmail.com
Classifier: Programming Language :: Python :: 3
Classifier: License :: OSI Approved :: MIT License
Classifier: Operating System :: OS Independent
Requires-Python: >=3.7
License-File: LICENSE
Requires-Dist: typing-extensions (<4.6.0,>=3.6.6)
Requires-Dist: cmake (>=3.27.2)
Requires-Dist: dlib
Requires-Dist: setuptools
Requires-Dist: retina-face
Requires-Dist: opencv-python
Requires-Dist: tensorflow
Requires-Dist: easyocr
Requires-Dist: Pillow
Requires-Dist: scikit-image
Requires-Dist: scipy
Requires-Dist: pandas
Requires-Dist: numpy
